[
    {
        "title": "Getting Started with React Hooks",
        "sub": ["useEffect", "useState", "useMemo"],
        "created": "2023-09-01T10:00:00Z",
        "updated": "2023-09-05T15:30:00Z",
        "contributors": ["githubUser1", "githubUser2"],
        "keywords": ["React", "Hooks", "useState", "useEffect", "useMemo"]
    },
    {
        "title": "Using Axios for API Requests",
        "sub": ["Introduction", "Axios"],
        "created": "2023-08-25T14:20:00Z",
        "updated": "2023-08-30T11:45:00Z",
        "contributors": ["githubUser3", "githubUser4"],
        "keywords": ["Axios", "API", "HTTP", "Request"]
    },
    {
        "title": "Responsive Web Design with CSS Grid",
        "sub": ["Grid Layout", "Media Queries"],
        "created": "2023-08-15T09:45:00Z",
        "updated": "2023-08-20T17:10:00Z",
        "contributors": ["githubUser5"],
        "keywords": ["CSS Grid", "Responsive Design", "Web Development"]
    },
    {
        "title": "Understanding JavaScript Promises",
        "sub": ["Introduction", "Chaining", "Error Handling"],
        "created": "2023-07-10T12:15:00Z",
        "updated": "2023-07-15T19:30:00Z",
        "contributors": ["githubUser6", "githubUser7"],
        "keywords": ["JavaScript", "Promises", "Async", "Programming"]
    },
    {
        "title": "MongoDB Basics for Beginners",
        "sub": ["Introduction", "CRUD Operations"],
        "created": "2023-06-20T11:30:00Z",
        "updated": "2023-06-25T14:45:00Z",
        "contributors": ["githubUser8"],
        "keywords": ["MongoDB", "Database", "NoSQL"]
    },
    {
        "title": "Python Flask: Building RESTful APIs",
        "sub": ["Getting Started", "Endpoints", "Authentication"],
        "created": "2023-06-05T13:40:00Z",
        "updated": "2023-06-10T16:55:00Z",
        "contributors": ["githubUser9", "githubUser10"],
        "keywords": ["Python", "Flask", "API", "REST"]
    },
    {
        "title": "Introduction to Machine Learning Algorithms",
        "sub": ["Regression", "Classification", "Clustering"],
        "created": "2023-05-15T08:50:00Z",
        "updated": "2023-05-20T12:05:00Z",
        "contributors": ["githubUser11", "githubUser12"],
        "keywords": ["Machine Learning", "Algorithms", "Data Science"]
    },
    {
        "title": "CSS Flexbox: Creating Flexible Layouts",
        "sub": ["Flex Containers", "Flex Items"],
        "created": "2023-05-01T16:25:00Z",
        "updated": "2023-05-05T20:40:00Z",
        "contributors": ["githubUser13"],
        "keywords": ["CSS Flexbox", "Layout", "Web Design"]
    },
    {
        "title": "Introduction to Java Programming",
        "sub": ["Syntax", "Object-Oriented Programming"],
        "created": "2023-04-10T09:10:00Z",
        "updated": "2023-04-15T14:20:00Z",
        "contributors": ["githubUser14", "githubUser15"],
        "keywords": ["Java", "Programming", "OOP"]
    },
    {
        "title": "Diving into Data Analysis with Pandas",
        "sub": ["Data Cleaning", "Exploratory Data Analysis"],
        "created": "2023-03-20T14:30:00Z",
        "updated": "2023-03-25T18:50:00Z",
        "contributors": ["githubUser16"],
        "keywords": ["Data Analysis", "Pandas", "Python"]
    }
]
